tgchizu/__init__.py
tgchizu/__main__.py
tgchizu/helper/__init__.py
tgchizu/helper/custom_filters.py
tgchizu/helper/config/__init__.py
tgchizu/helper/config/dynamic.py
tgchizu/helper/config/editor.py
tgchizu/helper/config/load.py
tgchizu/helper/config/reformatter.py
tgchizu/helper/config/subproc.py
tgchizu/helper/config/sync.py
tgchizu/helper/ext_utils/__init__.py
tgchizu/helper/ext_utils/bot_utils.py
tgchizu/helper/ext_utils/exceptions.py
tgchizu/helper/ext_utils/fs_utils.py
tgchizu/helper/mirror_utils/__init__.py
tgchizu/helper/mirror_utils/download_utils/__init__.py
tgchizu/helper/mirror_utils/download_utils/aria2_download.py
tgchizu/helper/mirror_utils/download_utils/direct_link_generator.py
tgchizu/helper/mirror_utils/download_utils/download_helper.py
tgchizu/helper/mirror_utils/download_utils/mega_download.py
tgchizu/helper/mirror_utils/download_utils/telegram_downloader.py
tgchizu/helper/mirror_utils/download_utils/youtube_dl_download_helper.py
tgchizu/helper/mirror_utils/status_utils/__init__.py
tgchizu/helper/mirror_utils/status_utils/aria_download_status.py
tgchizu/helper/mirror_utils/status_utils/extract_status.py
tgchizu/helper/mirror_utils/status_utils/listeners.py
tgchizu/helper/mirror_utils/status_utils/mega_download_status.py
tgchizu/helper/mirror_utils/status_utils/mega_status.py
tgchizu/helper/mirror_utils/status_utils/status.py
tgchizu/helper/mirror_utils/status_utils/tar_status.py
tgchizu/helper/mirror_utils/status_utils/telegram_download_status.py
tgchizu/helper/mirror_utils/status_utils/upload_status.py
tgchizu/helper/mirror_utils/status_utils/youtube_dl_download_status.py
tgchizu/helper/mirror_utils/upload_utils/__init__.py
tgchizu/helper/mirror_utils/upload_utils/gdriveTools.py
tgchizu/helper/telegram_helper/__init__.py
tgchizu/helper/telegram_helper/bot_commands.py
tgchizu/helper/telegram_helper/button_build.py
tgchizu/helper/telegram_helper/filters.py
tgchizu/helper/telegram_helper/message_utils.py
tgchizu/modules/__init__.py
tgchizu-1.5.5.dist-info/LICENSE
tgchizu-1.5.5.dist-info/METADATA
tgchizu-1.5.5.dist-info/WHEEL
tgchizu-1.5.5.dist-info/top_level.txt
tgchizu-1.5.5.dist-info/RECORD
