Metadata-Version: 2.1
Name: tgchizu
Version: 1.5.5
Summary: A Telegram Bot written in Python language to mirror files on the internet to Google Drive
Home-page: https://github.com/reaitten/tgchizu
Author: reaitten
Author-email: riojosepha@gmail.com
License: UNKNOWN
Project-URL: Bug Tracker, https://github.com/reaitten/tgchizu/issues
Platform: UNKNOWN
Classifier: Programming Language :: Python :: 3
Classifier: License :: OSI Approved :: GNU General Public License v3 (GPLv3)
Classifier: Operating System :: POSIX :: Linux
Classifier: Development Status :: 5 - Production/Stable
Requires-Python: >=3.8
Requires-Dist: requests
Requires-Dist: psutil
Requires-Dist: bs4
Requires-Dist: appdirs
Requires-Dist: python-telegram-bot (<14.0,>=13.0)
Requires-Dist: Pillow (>=4.2.0)
Requires-Dist: google-api-python-client (<2.0.0,>=1.12.8)
Requires-Dist: google-auth-httplib2 (<0.1.0,>=0.0.3)
Requires-Dist: google-auth-oauthlib (<0.10.0,>=0.4.1)
Requires-Dist: aria2p (<0.15.0,>=0.9.0)
Requires-Dist: python-dotenv (>=0.10)
Requires-Dist: tenacity (>=6.0.0)
Requires-Dist: python-magic
Requires-Dist: beautifulsoup4 (<4.8.10,>=4.8.2)
Requires-Dist: Pyrogram (<1.2.0,>=1.1.13)
Requires-Dist: TgCrypto (<2.0.0,>=1.2.2)
Requires-Dist: youtube-dl
Requires-Dist: feedparser
Requires-Dist: natsort
Requires-Dist: heroku3
Requires-Dist: aiohttp
Requires-Dist: speedtest-cli
Requires-Dist: messages
Requires-Dist: js2py
Requires-Dist: lxml
Requires-Dist: telegraph
Requires-Dist: pytz
Requires-Dist: megasdkrestclient (<1.0.0,>=0.1.1)
